envcloak/__init__.py
envcloak/cli.py
envcloak/comparator.py
envcloak/constants.py
envcloak/encryptor.py
envcloak/exceptions.py
envcloak/generator.py
envcloak/handlers.py
envcloak/loader.py
envcloak/utils.py
envcloak/validation.py
envcloak/version_check.py
envcloak/commands/__init__.py
envcloak/commands/compare.py
envcloak/commands/decrypt.py
envcloak/commands/encrypt.py
envcloak/commands/generate_key.py
envcloak/commands/generate_key_from_password.py
envcloak/commands/rotate_keys.py
envcloak/decorators/__init__.py
envcloak/decorators/common_decorators.py
examples/in_code/test.py
tests/conftest.py
tests/test_cli_compare.py
tests/test_cli_decrypt.py
tests/test_cli_dry_run.py
tests/test_cli_encrypt.py
tests/test_cli_encrypt_preview.py
tests/test_cli_generate_key.py
tests/test_cli_recursive_decrypt.py
tests/test_cli_recursive_encrypt.py
tests/test_cli_rotate_keys.py
tests/test_dynamic_analysis.py
tests/test_encryptor.py
tests/test_exceptions_encryptor.py
tests/test_exceptions_loader.py
tests/test_loader.py
tests/test_other_gitignore.py
tests/test_other_overwriting.py
tests/test_other_path_conflict.py
tests/test_pipeline_usage.py
envcloak-0.3.0.dist-info/LICENSE
envcloak-0.3.0.dist-info/METADATA
envcloak-0.3.0.dist-info/WHEEL
envcloak-0.3.0.dist-info/entry_points.txt
envcloak-0.3.0.dist-info/top_level.txt
envcloak-0.3.0.dist-info/RECORD
