Metadata-Version: 2.1
Name: envcloak
Version: 0.3.0
Summary: Securely manage encrypted environment variables with ease.
Author-email: "Konrad Kurek (Veinar)" <conrad.kurek+envcloak@gmail.com>
License:                                  Apache License
Project-URL: Homepage, https://github.com/Veinar/envcloak
Project-URL: Bug Tracker, https://github.com/Veinar/envcloak/issues
Project-URL: Documentation, https://github.com/Veinar/envcloak#readme
Keywords: environment-variables,encryption,security,cli-tool,python
Classifier: Development Status :: 4 - Beta
Classifier: Intended Audience :: Developers
Classifier: Intended Audience :: System Administrators
Classifier: Intended Audience :: Information Technology
Classifier: License :: OSI Approved :: Apache Software License
Classifier: Programming Language :: Python :: 3.9
Classifier: Programming Language :: Python :: 3.10
Classifier: Programming Language :: Python :: 3.11
Classifier: Programming Language :: Python :: 3.12
Classifier: Programming Language :: Python :: 3.13
Classifier: Topic :: Security
Classifier: Topic :: Software Development :: Build Tools
Requires-Python: >=3.9
License-File: LICENSE
Requires-Dist: click>=8.0.0
Requires-Dist: python-dotenv>=0.21.0
Requires-Dist: pyyaml>=5.4.1
Requires-Dist: cryptography>=3.4.7
Requires-Dist: defusedxml>=0.7.1
Requires-Dist: requests>=2.32.3
Requires-Dist: packaging>=24.2
Provides-Extra: dev
Requires-Dist: pytest>=6.0; extra == "dev"
Requires-Dist: bandit>=1.7.10; extra == "dev"
Requires-Dist: pylint>=3.3.1; extra == "dev"
Requires-Dist: black>=22.0; extra == "dev"
Requires-Dist: hypothesis>=6.0; extra == "dev"
